Workbook

Sheet 📊 Portfolio Analysis
A1: AI-Augmented Portfolio Intelligence System | L1: Scenario | N1: Balanced
A2: NSE India · Feb–May 2026 · MySQL + CAPM + WACC · ₹1,00,000 Portfolio | M2: → AI Signal Engine
A9: PORTFOLIO ALLOCATION · WHERE IS THE MONEY?
A26: SCENARIO COMPARISON · SAFETY vs GROWTH?
B32: +2.05% extra return · but +45% more market risk · Balanced wins on risk-adjusted basis
A36: RISK VERDICT · FULL VOLATILITY CLASSIFICATION
A38: asset_name | B38: asset_type | C38: avg_price | D38: max_price | E38: min_price | F38: price_range | G38: vol_percent | H38: Risk
A39: HDFC Bank Ltd | B39: Stock | C39: 807.02 | D39: 923.6 | E39: 731.55 | F39: 192.05 | G39: 0.23797428 | H39: {=_xlfn.IFS(Table1[[#This Row],[vol_percent]]>0.2," HIGH",Table1[[#This Row],[vol_percent]]>0.1," MEDIUM",Table1[[#This Row],[vol_percent]]>0.05," LOW ",TRUE," VERY LOW ")} -> HIGH
A40: Reliance Industries Ltd | B40: Stock | C40: 1380.4 | D40: 1463.6 | E40: 1304.6 | F40: 159 | G40: 0.115184 | H40: {=_xlfn.IFS(Table1[[#This Row],[vol_percent]]>0.2," HIGH",Table1[[#This Row],[vol_percent]]>0.1," MEDIUM",Table1[[#This Row],[vol_percent]]>0.05," LOW ",TRUE," VERY LOW ")} -> MEDIUM
A41: Nippon India Nifty BeES ETF | B41: Equity ETF | C41: 271.22 | D41: 290.45 | E41: 253.44 | F41: 37.01 | G41: 0.13645749 | H41: {=_xlfn.IFS(Table1[[#This Row],[vol_percent]]>0.2," HIGH",Table1[[#This Row],[vol_percent]]>0.1," MEDIUM",Table1[[#This Row],[vol_percent]]>0.05," LOW ",TRUE," VERY LOW ")} -> MEDIUM
A42: Nippon India Gold BeES ETF | B42: Commodity ETF | C42: 125.95 | D42: 138.32 | E42: 110.72 | F42: 27.6 | G42: 0.21913458 | H42: {=_xlfn.IFS(Table1[[#This Row],[vol_percent]]>0.2," HIGH",Table1[[#This Row],[vol_percent]]>0.1," MEDIUM",Table1[[#This Row],[vol_percent]]>0.05," LOW ",TRUE," VERY LOW ")} -> HIGH
A43: Motilal Oswal Silver ETF | B43: Commodity ETF | C43: 63.65 | D43: 64.19 | E43: 62.88 | F43: 1.31 | G43: 0.020581304 | H43: {=_xlfn.IFS(Table1[[#This Row],[vol_percent]]>0.2," HIGH",Table1[[#This Row],[vol_percent]]>0.1," MEDIUM",Table1[[#This Row],[vol_percent]]>0.05," LOW ",TRUE," VERY LOW ")} -> VERY LOW
A45: Data: NSE India · Risk-Free: 7% RBI G-Sec · Feb–May 2026 MySQL + Power Query + Excel + AI → AI Signal Engine

Sheet AI Signal Engine
A1: AI Investment Signal Engine | J1: ChatGPT · Live AI
A2: MySQL Price Data → Power Query → ChatGPT AI Add-in → Real-Time Investment Intelligence | J2: ← Portfolio Analysis
A3: NSE CSV Data | B3: → | C3: MySQL Database | D3: → | E3: Power Query | F3: → | G3: ChatGPT for Sheets | H3: → | I3: Live Investment Intelligence
A6: MACRO MARKET CONTEXT · KEY FACTORS DRIVING YOUR PORTFOLIO
A17: AI SIGNAL TABLE · ChatGPT-POWERED CONVICTION RATINGS
A19: Asset Name | B19: Type | C19: 3M Return | D19: ▲▼ | E19: Sentiment | F19: AI Signal | G19: Conviction | H19: Time Horizon
A20: =INDEX(Query111[asset_name],1) -> Nippon India Nifty BeES ETF | B20: =INDEX(Query111[asset_type],1) -> Equity ETF | C20: =TEXT(INDEX(Query111[#All],2,7),"+0.0%;-0.0%") -> +14.6% | D20: =IF(INDEX(Query111[return_3m],1)>0,"↑","↓") -> ↑ | E20: Bullish | F20: INCREASE | G20: HIGH ★★★ | H20: 3-6 months
A21: =INDEX(Query111[asset_name],2) -> Nippon India Gold BeES ETF | B21: =INDEX(Query111[asset_type],2) -> Commodity ETF | C21: =TEXT(INDEX(Query111[#All],3,7),"+0.0%;-0.0%") -> +24.9% | D21: =IF(INDEX(Query111[return_3m],2)>0,"↑","↓") -> ↑ | E21: Bullish | F21: STRONG HOLD | G21: HIGH ★★★ | H21: 3-6 months
A22: =INDEX(Query111[asset_name],3) -> Motilal Oswal Silver ETF | B22: =INDEX(Query111[asset_type],3) -> Commodity ETF | C22: =TEXT(INDEX(Query111[#All],4,7),"+0.0%;-0.0%") -> +2.1% | D22: =IF(INDEX(Query111[return_3m],3)>0,"↑","↓") -> ↑ | E22: Neutral | F22: HOLD | G22: MED ★★☆ | H22: 1-3 months
A23: =INDEX(Query111[asset_name],4) -> HDFC Bank Ltd | B23: =INDEX(Query111[asset_type],4) -> Stock | C23: =TEXT(INDEX(Query111[#All],5,7),"+0.0%;-0.0%") -> -26.3% | D23: =IF(INDEX(Query111[return_3m],4)>0,"↑","↓") -> ↓ | E23: Bearish | F23: REDUCE | G23: LOW ★☆☆ | H23: 1-3 months
A24: =INDEX(Query111[asset_name],5) -> Reliance Industries Ltd | B24: =INDEX(Query111[asset_type],5) -> Stock | C24: =TEXT(INDEX(Query111[#All],6,7),"+0.0%;-0.0%") -> -12.2% | D24: =IF(INDEX(Query111[return_3m],5)>0,"↑","↓") -> ↓ | E24: Cautious | F24: HOLD & WATCH | G24: MED ★★☆ | H24: 1-3 months
A26: AI NEWS DIGEST · CHATGPT-GENERATED MARKET INTELLIGENCE PER ASSET
A28: NiftyBEES ETF IMPACT: POSITIVE Headline: "NiftyBEES tracks firmer Nifty as FII buying, softer VIX and 6.25% RBI rate support accumulation" Source: Business Standard · 20 days ago Action: ADD on dips | G28: GoldBEES ETF IMPACT: POSITIVE Headline: "GoldBEES gains defensive bid as strong three-month returns keep bullion allocations resilient despite calmer equity volatility" Source: WisdomTree · 7 days ago Action: HOLD firmly
A36: HDFC Bank IMPACT: NEGATIVE Headline: "HDFC Bank underperformance deepens as high beta and weak momentum keep private-bank exposure under pressure" Source: Moneycontrol · 35 days ago Action: REDUCE position | G36: Reliance Ind. IMPACT: NEUTRAL Headline: "Reliance stays range-bound as recent profit softness offsets heavyweight support from improving domestic risk appetite" Source: Business Standard · 30 days ago Action: WAIT & WATCH
A47: 📝 PORTFOLIO NARRATIVE & VERDICT
A48: The portfolio reflects a balanced construction, with ₹1,00,000 invested, expected return of 11.49%, and portfolio beta of 0.75, indicating moderated market sensitivity. Performance is led by Nippon India GoldBEES at +24.9% and NiftyBEES at +14.6%, supported by FII net buying of ₹8,420Cr and the RBI’s 25 bps repo cut. The main concern is HDFC Bank, down 26.3%, where rising NPAs and regulatory pressure warrant a reduction in exposure. Secondary risk comes from Reliance Industries, down 12.2%, as Jio ARPU softness and O2C margin pressure could cap near-term upside. Recommendation is to rebalance by reducing HDFC Bank from 20% to 12% and increasing NiftyBEES from 30% to 38%, while retaining a balanced risk profile. Generated by ChatGPT · Based on MySQL 3M price data + Macro context · May 2026 · Not financial advice
A60: HOW TO REFRESH AI DATA — STEP-BY-STEP GUIDE
A62: ChatGPT Prompt Summary (what to ask) | Paste Result Into (cell + format)
A63: · AI Signal Table Analyse 5 Indian assets (NiftyBEES +14.6%, GoldBEES +24.9%, Silver +2.1%, HDFC -26.3%, Reliance -12.2%). Give Signal, Conviction, and Time Horizon. Macro: RBI 6.25%, VIX 14.2. | Signal (F), Conviction (G), Horizon (H), rows 20–24. Bold, centre-aligned, colour-coded background.
A65: News Digest Write 4 news headlines (max 20 words each) for NiftyBEES, GoldBEES, HDFC Bank, Reliance. Include source, days ago, and action. May 2026 context. | 4 merged news card cells. Calibri 8pt, wrap text ON, left border colour matches impact.
A67: Portfolio Narrative Write 5-sentence research note. Portfolio: ₹1,00,000, beta 0.75, return 11.49%. Gold and NiftyBEES working. HDFC main concern. Recommend reduce HDFC and increase NiftyBEES. | Large merged narrative cell. Calibri 9pt, wrap text ON, light blue fill, thick navy left border, row height 90pt.
A69: How to Refresh (all sections) | Open ChatGPT sidebar in Excel → click New Chat → paste the relevant prompt above → copy the output → click target cell in Excel → paste → press Enter. Takes 2 minutes per section. | Instruction row only — no paste needed. For interviewer reference only.
A72: Data: NSE India · Risk-Free: 7% RBI G-Sec · Feb–May 2026 MySQL + Power Query + Excel + AI → AI Signal Engine
A177: asset_name | B177: asset_type | C177: avg_price | D177: max_price | E177: min_price | F177: price_range | G177: return_3m
A178: Nippon India Nifty BeES ETF | B178: Equity ETF | C178: 271.22 | D178: 290.45 | E178: 253.44 | F178: 37.01 | G178: 0.146
A179: Nippon India Gold BeES ETF | B179: Commodity ETF | C179: 125.95 | D179: 138.32 | E179: 110.72 | F179: 27.6 | G179: 0.2493
A180: Motilal Oswal Silver ETF | B180: Commodity ETF | C180: 63.65 | D180: 64.19 | E180: 62.88 | F180: 1.31 | G180: 0.0208
A181: HDFC Bank Ltd | B181: Stock | C181: 807.02 | D181: 923.6 | E181: 731.55 | F181: 192.05 | G181: -0.2625
A182: Reliance Industries Ltd | B182: Stock | C182: 1380.4 | D182: 1463.6 | E182: 1304.6 | F182: 159 | G182: -0.1219

Sheet HELPER
A3: Scenario Selector | B3: ='📊 Portfolio Analysis'!N1 -> Balanced
A5: Dynamic Weights Table
A6: Asset Name | B6: Weight % | C6: Expected Return % | D6: Weighted Return
A7: =asset_data!B2 -> Nippon India Nifty BeES ETF | B7: =IF($B$3="Balanced",30,50) -> 30 | C7: =IF($B$3="Balanced",13,13) -> 13 | D7: =IF($B$3="Balanced",3.9,6.5) -> 3.9
A8: =asset_data!B3 -> Nippon India Gold BeES ETF | B8: =IF($B$3="Balanced",25,0) -> 25 | C8: =IF($B$3="Balanced",7.3,7.3) -> 7.3 | D8: =IF($B$3="Balanced",1.83,0) -> 1.83
A9: =asset_data!B4 -> Motilal Oswal Silver ETF | B9: =IF($B$3="Balanced",10,0) -> 10 | C9: =IF($B$3="Balanced",8.5,8.5) -> 8.5 | D9: =IF($B$3="Balanced",0.85,0) -> 0.85
A10: =asset_data!B5 -> HDFC Bank Ltd | B10: =IF($B$3="Balanced",20,30) -> 20 | C10: =IF($B$3="Balanced",14.8,14.8) -> 14.8 | D10: =IF($B$3="Balanced",2.96,4.44) -> 2.96
A11: =asset_data!B6 -> Reliance Industries Ltd | B11: =IF($B$3="Balanced",15,20) -> 15 | C11: =IF($B$3="Balanced",13,13) -> 13 | D11: =IF($B$3="Balanced",1.95,2.6) -> 1.95
A13: KPI Formulas
A14: Expected Return % | B14: =IF($B$3="Balanced",11.49,13.54) -> 11.49
A15: Portfolio Beta | B15: =IF($B$3="Balanced",0.75,1.09) -> 0.75
A16: ASSETS | B16: 5
A17: Gold+Silver % | B17: =IF($B$3="Balanced",35,0) -> 35
A18: Above Risk-Free % | B18: ="+" & IF($B$3="Balanced",4.49,6.54)&"%" -> +4.49%
A20: MACRO INPUT — UPDATE ONLY HERE
A21: RBI Repo Rate | B21: 0.0625 | C21: Source: RBI Feb 2026
A22: India VIX | B22: 14.2 | C22: Source: NSE India May 2026
A23: FII Net Flow | B23: +₹8420 Cr | C23: Source: NSDL May 2026
A24: USD/INR Rate | B24: 95.07 | C24: Source: RBI May 2026

Sheet 2 CASES
A1: asset_name | B1: balanced_weight | C1: aggressive_weight
A2: Nippon India Nifty BeES ETF | B2: 30 | C2: 50
A3: Nippon India Gold BeES ETF | B3: 25 | C3: 0
A4: Motilal Oswal Silver ETF | B4: 10 | C4: 0
A5: HDFC Bank Ltd | B5: 20 | C5: 30
A6: Reliance Industries Ltd | B6: 15 | C6: 20

Sheet etf_vs_stock
A1: asset_type | B1: total_assets | C1: average_price
A2: Equity ETF | B2: 1 | C2: 271.22
A3: Commodity ETF | B3: 2 | C3: 94.8
A4: Stock | B4: 2 | C4: 1093.71

Sheet SECTOR
A1: asset_name | B1: price_range | C1: sector
A2: HDFC Bank Ltd | B2: 192.05 | C2: Banking
A3: Reliance Industries Ltd | B3: 159 | C3: Energy & Telecom
A4: Nippon India Nifty BeES ETF | B4: 37.01 | C4: Broad Market
A5: Nippon India Gold BeES ETF | B5: 27.6 | C5: Gold
A6: Motilal Oswal Silver ETF | B6: 1.31 | C6: Silver

Sheet scenario_summary
A1: portfolio_type | B1: expected_return_percent | C1: weighted_portfolio_beta
A2: Balanced | B2: 11.49 | C2: 0.7475
A3: Aggressive | B3: 13.54 | C3: 1.09

Sheet PORTFOLIO WACC
A1: scenario | B1: asset_name | C1: beta | D1: expected_return | E1: weight_percent | F1: weighted_return
A2: Balanced | B2: Nippon India Nifty BeES ETF | C2: 1 | D2: 13 | E2: 30 | F2: 3.9
A3: Balanced | B3: Nippon India Gold BeES ETF | C3: 0.05 | D3: 7.3 | E3: 25 | F3: 1.83
A4: Balanced | B4: Motilal Oswal Silver ETF | C4: 0.25 | D4: 8.5 | E4: 10 | F4: 0.85
A5: Balanced | B5: HDFC Bank Ltd | C5: 1.3 | D5: 14.8 | E5: 20 | F5: 2.96
A6: Balanced | B6: Reliance Industries Ltd | C6: 1 | D6: 13 | E6: 15 | F6: 1.95
A7: Aggressive | B7: Nippon India Nifty BeES ETF | C7: 1 | D7: 13 | E7: 50 | F7: 6.5
A8: Aggressive | B8: Nippon India Gold BeES ETF | C8: 0.05 | D8: 7.3 | E8: 0 | F8: 0
A9: Aggressive | B9: Motilal Oswal Silver ETF | C9: 0.25 | D9: 8.5 | E9: 0 | F9: 0
A10: Aggressive | B10: HDFC Bank Ltd | C10: 1.3 | D10: 14.8 | E10: 30 | F10: 4.44
A11: Aggressive | B11: Reliance Industries Ltd | C11: 1 | D11: 13 | E11: 20 | F11: 2.6

Sheet asset_data
A1: asset_id | B1: asset_name | C1: asset_type | D1: sector | E1: avg_price | F1: max_price | G1: min_price | H1: avg_volume | I1: total_days | J1: invested_amt | K1: weight_percent
A2: 1 | B2: Nippon India Nifty BeES ETF | C2: Equity ETF | D2: Broad Market | E2: 271.22 | F2: 290.45 | G2: 253.44 | H2: 10000000 | I2: 57 | J2: 30000 | K2: 30
A3: 2 | B3: Nippon India Gold BeES ETF | C3: Commodity ETF | D3: Gold | E3: 125.95 | F3: 138.32 | G3: 110.72 | H3: 50160304 | I3: 57 | J3: 25000 | K3: 25
A4: 3 | B4: Motilal Oswal Silver ETF | C4: Commodity ETF | D4: Silver | E4: 63.65 | F4: 64.19 | G4: 62.88 | H4: 52713 | I4: 57 | J4: 10000 | K4: 10
A5: 4 | B5: HDFC Bank Ltd | C5: Stock | D5: Banking | E5: 807.02 | F5: 923.6 | G5: 731.55 | H5: 46082512 | I5: 57 | J5: 20000 | K5: 20
A6: 5 | B6: Reliance Industries Ltd | C6: Stock | D6: Energy & Telecom | E6: 1380.4 | F6: 1463.6 | G6: 1304.6 | H6: 19000000 | I6: 57 | J6: 15000 | K6: 15

Sheet GPT cache

Sheet __bpstmp_o5xy01_10
